xliff_linter/__init__.py
xliff_linter/linter.py
moz_xliff_linter-0.1.1.dist-info/METADATA
moz_xliff_linter-0.1.1.dist-info/WHEEL
moz_xliff_linter-0.1.1.dist-info/entry_points.txt
moz_xliff_linter-0.1.1.dist-info/top_level.txt
moz_xliff_linter-0.1.1.dist-info/RECORD
