Metadata-Version: 2.2
Name: moz-xliff-linter
Version: 0.1.1
Summary: Linter package used to check XLIFF files
Home-page: https://github.com/mozilla-l10n/moz-xliff-linter
Author: Francesco Lodolo
Author-email: flod@mozilla.com
Project-URL: Bug Tracker, https://github.com/mozilla-l10n/moz-xliff-linter/issues
Classifier: Intended Audience :: Developers
Classifier: License :: OSI Approved :: Mozilla Public License 2.0 (MPL 2.0)
Classifier: Operating System :: OS Independent
Classifier: Programming Language :: Python :: 3
Classifier: Topic :: Software Development :: Libraries :: Python Modules
Classifier: Topic :: Software Development :: Localization
Requires-Python: >=3.11
Requires-Dist: lxml
